{
    "3": {
        "0": [
            "Eu tinha planejado em me segurar, mas no final, ",
            "Eu não pude resistir. Antes que eu percebesse, ",
            "Eu já estava no banheiro."
        ],
        "1": [
            "Mesmo sendo um lugar familiar, ",
            "entrar escondido assim",
            "faz tudo parecer excitante e novo …"
        ],
        "2": [
            "Eu consegui entrar, silenciosamente, passo a passo…!",
            "Certo, infiltração bem sucedida…!"
        ],
        "3": [
            "Não vai demorar para a \\str[120] sair… ",
            "Eu devo sair do banheiro?"
        ],
        "4": [
            "Sair",
            "Esquece"
        ],
        "5": [
            "Isso é o suficiente por hoje—ser pego pela ",
            "\\str[120] seria ruim."
        ],
        "6": [
            "Yeah, Não vai demorar para a \\str[120] sair——"
        ],
        "7": [
            "Talvez eu fique mais um pouquinho…"
        ],
        "8": [
            "Eu já me infiltrei no banheiro.",
            "Tenho que ficar em silêncio para \\str[120] não me perceber…"
        ],
        "9": [
            "Dançar!",
            "Meditar",
            "Continuar Assistindo"
        ],
        "10": [
            "Hmm… Eu preciso ser extremamente cuidadoso,",
            "eu não quero deixar a \\str[120] desconfiada…"
        ],
        "11": [
            "Yeah… Eu preciso me acalmar.",
            "Hora de meditar—  \\w[30]"
        ],
        "12": [
            "No mundo da meditação, eu estou sozinho.",
            "Isso sempre traz paz para minha mente…"
        ],
        "13": [
            "……………………",
            "……………………"
        ],
        "14": [
            "Whoa, intensivando o foco,",
            "até o som do chuveiro no banheiro ",
            "é limpo e cristalino. Eu até consigo ouvir a",
            "voz da \\str[120] perfeitamente—"
        ],
        "15": [
            "Isso só me fez ficar ainda mais excitado…"
        ],
        "16": [
            "A tensão está ficando muito intensa… ",
            "Eu preciso encontrar algo para me distrair.",
            "Ok, então—\\w[60]\\{vamos dançar!"
        ],
        "17": [
            "\\{Aqui nesse banheiro!",
            "Neste lugar apertado cheio de perigos!",
            "Move my body!",
            "Afiar meus sentidos de ninja e me equilibrar!"
        ],
        "18": [
            "\\{Aqui nesse banheiro!",
            "Neste lugar apertado cheio de perigos!",
            "Deixar meu corpo se mover livremente!"
        ],
        "19": [
            "\\{...Hah!\\w[60] Hah!  \\w[60]"
        ],
        "20": [
            "Respiração, coração movimento—tudo em perfeita sincronia.",
            "Isso não é só mais um treinamento. É uma arte.",
            "Só um verdadeiro ninja conseguiria fazer um ",
            "ato tão perigoso!"
        ],
        "21": [
            "—\\str[120] nunca saberá.",
            "Que um dia, uma sombra dançou logo atrás dela",
            "e desapareceu despercebidamente."
        ],
        "22": [
            "Meus passos ecoavam e desapareciam com cada movimento.",
            "Isso não é somente uma dança…",
            "É um ritual—um tributo à arte da furtividade."
        ],
        "23": [
            "…\\str[120] ainda não notou nada.",
            "Agora eu posso ir e vir nessa casa sem emitir um único som."
        ],
        "24": [
            "Eu sou a sombra! Eu sou o vento! Eu sou— \\w[60]",
            "…Não, Eu sou só um idiota dançando no banheiro…"
        ],
        "25": [
            "…Pensando bem, ",
            "talvez eu tenha me deixado levar por isso?"
        ],
        "26": [
            "…Parece que eu aprimorei minha habilidade de furtividade ",
            "só um pouco."
        ],
        "27": [
            "…Ugh! Eu escorreguei, quase bati na ",
            "máquina de lavar…!"
        ],
        "28": [
            "Ufa, essa sensação de tirar o fôlego…",
            "traz um sentimento de conquista.",
            "Meio emocionante na verdade?"
        ]
    },
    "11": {
        "0": [
            "Depois de lavar seu rosto, ",
            "\\str[120] parece muito mais energética.",
            "Agora, estamos de pé, lado a lado, ",
            "escovando os dentes em frente ao espelho."
        ],
        "1": [
            "Compartilhar uma rotina matinal com ela dessa forma ",
            "é muito raro, e por um momento, me fez sentir um pouco inquieto.",
            "Bem… Acho que vou só bater um papo—"
        ],
        "2": [
            "\"Qu vam cmer d caf da munhu...\""
        ],
        "3": [
            "\nl< >\"Nu sai... nu pnse em nd'... inda...\"  \\w[330]\\^"
        ],
        "4": [
            "\"iss scova dus lads... é fca lipo...\""
        ],
        "5": [
            "\nl< >\"O-nii-cha... você é... único—!\"    \\w[330]\\^"
        ],
        "6": [
            "Hmm… Eu não consegui entender porra nenhuma.",
            "Estando com a boca cheia de espuma ",
            "fica bem difícil de falar."
        ],
        "7": [
            "Terminamos de escovar os dentes enquanto conversando em ",
            "linguas que nenhum de nós conseguia entender."
        ]
    },
    "13": {
        "0": [
            "\nl< >\"...Uma pegadinha nova, huh?\""
        ],
        "1": [
            "Mesmo que \\str[120] ainda fique fazendo doce,",
            "ela só me xingou um pouco em vez de me chutar pra fora como antes."
        ],
        "2": [
            "Entendi—ela só é envergonhada.",
            "Ela só precisa de um empurrãozinho ",
            "em um momento como esse!"
        ],
        "3": [
            "\"Na verdade, ",
            "Acho que fui amaldiçoado por um arquidemônio na floresta novamente.\""
        ],
        "4": [
            "Bem na minha frente \\str[120], ",
            "Eu baixei minhas calças em um movimento,",
            "puxando meu pau duraço e pulsante."
        ],
        "5": [
            "\nl< >\"Eh?! \\str[121]...!    \\w[30]",
            "Por que você está se pelando aqui...?!\""
        ],
        "6": [
            "Ela parecia |estonteada|, querendo cobrir seus olhos,",
            "mas ela não podia mover suas mãos porque ",
            "estava ocupada cobrindo seus peitos."
        ],
        "7": [
            "\"Aquele maldido demonio me amaldiçoou, ",
            "fez meu pau virar uma bomba Relógio.",
            "Se não resolvermos isso agora, toda a casa pode explodir!\""
        ],
        "8": [
            "\nl< >\"...E-Então, o que vamos fazer?\""
        ],
        "9": [
            "\"Só use sua mão. ",
            "Se você ficar acariciando ele, vai sair...\""
        ],
        "10": [
            "\nl< >\"Por que você não pode usar tua mão, \\str[121]?\""
        ],
        "11": [
            "A resposta repentina dela me deixou sem palavras."
        ],
        "12": [
            "Talvez ficar enganando ela com muitas mentiras idiotas",
            "deixou ela mais espertinha...?!"
        ],
        "13": [
            "\"Eu me sentiria menos estranho se   \\}",
            "as mãos fofas da \\str[120] fizessem isso.\""
        ],
        "14": [
            "Minha voz foi sumindo, ficando mais e mais silenciosa."
        ],
        "15": [
            "\nl< >\"Isso parece muito suspeito... \\str[121], ",
            "você está tentando mexer comigo de novo?\""
        ],
        "16": [
            "As suspeitas dela estavam crescendo, se eu não fizesse algo,",
            "ela certamente me chutaria pra fora..."
        ],
        "17": [
            "\nl< >\"Que—?! \\str[121], isso é...!\""
        ],
        "18": [
            "\"Enquanto você ta se fazendo, ",
            "seu \\str[121]'s tá sofrendo com essa maldição, percebeu né.",
            "Você vai mesmo ficar parada ficar me vendo sofrer?\""
        ],
        "19": [
            "Eu fiz a cara mais inocente e sofrida enquanto chegava mais perto",
            "então eu apertei meu pau já dolorido em seu rosto ,",
            "esfregando nela sem parar."
        ],
        "20": [
            "\nl< >\"Mas... \\str[121], você realmente não parece estar sofrendo...   \\w[120]",
            "E para de esfregar coisas estranhas na minha cara…!\""
        ],
        "21": [
            "\"Olha~ até meu pau tá tremendo, ele tá quase explodindo, viu?\""
        ],
        "22": [
            "\nl< >\"Mm... mmmph...\""
        ],
        "23": [
            "\"Se explodir, nossa querida casa vai desaparecer pra sempre, sabe né.\""
        ],
        "24": [
            "\nl< >\"...Jeez, \\str[121], você está sempre...     \\w[60]",
            "mentindo descaradamente com a cara séria...\""
        ],
        "25": [
            "Seu rosto ficou corado, até suas orelhas estavam avermelhadas,",
            "e ela não estava nem revidando—só um último empurrão...",
            "Só mais um passo e sua concha de timidez vai rachar para!"
        ],
        "26": [
            "\\str[120] Coupon #ToDo ???",
            "Me prometa",
            "Subornar com dinheiro"
        ],
        "27": [
            "\nl< >\"...Táa, eu entendi...    \\w[60]",
            "Eu vou te ajudar, mas só dessa vez...\""
        ],
        "28": [
            "Acho que o suborno funcionou,",
            "sua resposta não tinha mais nenhum sinal de resistência."
        ],
        "29": [
            "\nl< >\"...Isso é bom o suficiente?\""
        ],
        "30": [
            "Ela gentilmente envolveu meu pau com suas pequenas mãos,",
            "certamente desconhecendo esse tipo de coisas."
        ],
        "31": [
            "Só sua palma suave e quente envolvendo meu pau ",
            "era o suficiente pra me fazer vibrar de excitação."
        ],
        "32": [
            "\"Só ficar segurando não vai ser suficiente—",
            "você precisa mover sua mão pra cima e pra baixo.\""
        ],
        "33": [
            "Vendo sua confusão, eu tive que pegar nas suas mãos e ",
            "demonstrar pra ela o movimento para cima e para baixo."
        ],
        "34": [
            "\nl< >\"............??\""
        ],
        "35": [
            "\nl< >\"Ti-Tipo assim?\""
        ],
        "36": [
            "Ela lentamente começou a apertar e mover meu pau ",
            "com movimentos desajeitados, mas sentindo o seu calor ",
            "tão próximo de mim quase me fez perder a cabeça."
        ],
        "37": [
            "\nl< >\"...Por quanto tempo eu preciso ficar fazendo isso?\""
        ],
        "38": [
            "\"Sem pressa... Estou quase lá—\""
        ],
        "39": [
            "Parece que ela começou a pegar o jeito e aumentou a velocidade, ",
            "a repentina onda de prazer me levou ao limite ",
            "antes que eu pudesse a avisar—"
        ],
        "40": [
            "\nl< >\"...Eh?     \\w[30]\\{",
            "Nnngyaaaaaaa—\""
        ],
        "41": [
            "Ela ficou em pânico com os gigantes e repentinos jatos de porra, ",
            "ela instintivamente tentou cobrir com suas mãos, ",
            "tentando evitar que a porra se espalhasse pra todo lado."
        ],
        "42": [
            "\"Está tudo bem, essa coisa realmente não é perigosa—",
            "\\w[20]\\^"
        ],
        "43": [
            "\nl< >\"—O pau do \\str[121] realmente explodiu?! ",
            "E meus olhos...?! Tá tão quente e grudento ahhhh...!!\""
        ],
        "44": [
            "\"Ooooohhhhhhhhhh—?!\""
        ],
        "45": [
            "Assustada, ela me apertou ainda mais forte, ",
            "a dor parecia torcer o meu mau me fez ",
            "gritar junto com ela."
        ],
        "46": [
            "\"Nnnngyaaaaaa—\"",
            "\"Ooooohhhhhhhhhh—\""
        ],
        "47": [
            "\nl< >\"Ugh, Eu to toda grudenta agora...    \\w[90]",
            "E tudo culpa sua, \\str[121], ",
            "você não me disse que isso ia acontecer...\""
        ],
        "48": [
            "\"Ah... ahhh... É, você não está errada sobre isso...\""
        ],
        "49": [
            "Quase sem conseguir responder, minha mente ficou em branco, ",
            "mesmo ela me fazendo sentir incrível a poucos momentos atrás,",
            "aquele pequeno acidente quase me traumatizou pro resto da vida..."
        ],
        "50": [
            "\nl< >\"Ok! Se você já tá pronto, cai fora agora!   \\w[60]",
            "Eu preciso tomar banho!!\""
        ],
        "51": [
            "Mas...Eu meio que queria... tomar banho junto com você..."
        ],
        "52": [
            "Eu tenho quase certeza que se tomássemos banho juntos agora,",
            "as coisas ficariam ainda mais estranhas, mas ela já me",
            "chutou do banheiro."
        ]
    },
    "15": {
        "0": [
            "Ah, falando nisso… entre as coisas aleatórios e sem sentido ",
            "que a menina ninja me ensinou era algo chamado, ",
            "o 'Princípio Estrutural da Porta Ninja' que realmente ",
            "pareceu muito interessante.",
            "talvez eu possa alterar a porta do banheiro usando isso—"
        ],
        "1": [
            "Tipo, se eu conseguir entalhar uma pequena perfuração ",
            "em um ângulo que só eu consiga visualizar—",
            "Contanto que eu consiga fazer isso cuidadosamente e sem estragar ",
            "a proteção sonora e a impermeabilização… Então eu poderia—",
            "\\{ Hehehehe~~~~~"
        ],
        "2": [
            "\\{Ahem!\\}\\w[45] Não que eu faria isso por uma razão estranha.",
            "Só no caso que a \\str[120] desmaie durante o ",
            "banho— Eu preciso poder perceber isso imediatamente.",
            "É totalmente por razões de segurança! Isso, é isso mesmo!"
        ],
        "3": [
            "\\{ok!",
            "hora de ir trabalhar enquanto eu ainda posso!"
        ],
        "4": [
            "Phew… isso foi o suficiente pra hoje. ",
            "Se eu ficar muito tempo, a \\str[120] pode suspeitar.",
            "Só mais duas ou três modificações ",
            "e deve estar perfeito pra usar~~!"
        ],
        "5": [
            "A modificação da porta ninja de ontem parece ter funcionado bem.",
            "Hora de fazer mais modificações!"
        ],
        "6": [
            "Whew…! Essa passou perto. ",
            "Eu quase furei um buraco na parede do lado.",
            "Ainda bem que a \\str[120] não veio bater na porta…"
        ],
        "7": [
            "É o suficiente pra hoje. Se eu ficar muito tempo nisso, ",
            "ela pode começar a suspeitar de algo.",
            "Só mais um turno de desenvolvimento e ",
            "deve ficar pronto~~!"
        ],
        "8": [
            "Certo… hoje é a reta final.",
            "O grosso já foi feito—só preciso raspar ",
            "a última camada e então instalar um filme ",
            "semi-transparente para que a \\str[120] não note."
        ],
        "9": [
            "…Pronto! O ângulo da visão está perfeito ",
            "e está completamente escondido",
            "Eu consigo ver o banheiro todo desse ângulo!",
            "Parece que está pronto pra inaugurar amanhã~!"
        ],
        "10": [
            "Mas claro, eu só estou fazendo isso por preocupação ",
            "com a saúde e o bem estar da \\str[120]!",
            "Definitivamente pra nada estranho!"
        ],
        "11": [
            "Suei bastante nessa—hora pra tomar um banho!"
        ],
        "12": [
            "Ton Ton Ton Ton Ton Ton Ton~~!"
        ]
    },
    "17": {
        "0": [
            "\\str[120] está quase acabando seu banho..",
            "Melhor sair rápido daqui."
        ],
        "1": [
            "Eu não consigo mais ver a \\str[120] pela porta do banheiro...",
            "Parece que ela está mergulhada na banheira."
        ],
        "2": [
            "Eu consigo ver a \\str[120] pela porta do banheiro",
            "Parece que ela ainda está se lavando..."
        ],
        "3": [
            "\\str[120] ainda não me notou parado na frente da ",
            "porta do banheiro.",
            "O que eu devo fazer?"
        ],
        "4": [
            "Invadir!",
            "Espiar",
            "Voltar"
        ],
        "5": [
            "Ok então... só uma espiadinha..."
        ],
        "6": [
            "A silhueta da \\str[120] é claramente visível pelo",
            "vidro. Despertando todo tipo de imaginação."
        ],
        "7": [
            "Continuar Explorando",
            "Hora de Voltar"
        ],
        "8": [
            "Tudo limpo, vamos continuar explorando!"
        ],
        "9": [
            "\\str[120] terminou seu banho, ",
            "Eu preciso sair rápido daqui."
        ],
        "10": [
            "...Ohhh! Eu consigo ver ela!"
        ],
        "11": [
            "\\str[120] está cuidadosamente esfregando seus braços."
        ],
        "12": [
            "Sabonete Corporal?",
            "Já tem muita espuma, ",
            "está muito difícil de ver os detalhes…"
        ],
        "13": [
            "\\str[120] ainda está esfregando seus peitos cuidadosamente…",
            "Isso parece tão obsceno…"
        ],
        "14": [
            "...Ainda continuar espiando?"
        ],
        "15": [
            "Continuar espiando",
            "Usar a porta ninja",
            "Parar de espiar"
        ],
        "16": [
            "…\\str[120] está começando a perceber minha presença.",
            "Melhor parar de espiar."
        ],
        "17": [
            "\\str[120] foi pra banheira.",
            "Ela está alegremente cantarolando uma melodia."
        ],
        "18": [
            "…Já é hora.",
            "\\str[120] está quase pronta, melhor eu voltar."
        ],
        "19": [
            "Esse é o momento perfeito para utilizar a ",
            "porta ninja e aproveito isso tudo novamente…!"
        ],
        "20": [
            "—Eu já não tenho feito bom uso?"
        ],
        "21": [
            "\\str[120] ainda está cuidadosamente esfregando seus peitos…",
            "Isso parece tão obsceno…"
        ]
    },
    "23": {
        "0": [
            "De mansinho e quietinho…………  \\w[30]",
            "Se eu vou espiar, eu preciso abrir a porta cuidadosamente ",
            "pra que a \\str[120] não me perceba—"
        ],
        "1": [
            "Oh oh oh—! Eu consigo ver ela!",
            "Parece que a \\str[120] está prestes a tirar a calcinha.",
            "Eu imagino se vou conseguir ver sua buceta desse ângulo!?"
        ],
        "2": [
            "Oh oh oh—! Eu consigo ver ela!",
            "Parece que a \\str[120] está prestes a tirar suas roupas.",
            "Não é comum eu conseguir ver ela só de calcinha… ",
            "Será que eu consigo ver o momento que ela vai tirar elas!?"
        ],
        "3": [
            "Oh oh oh—! Eu consigo ver ela!",
            "Parece que a \\str[120] está prestes a tirar suas roupas.",
            "Sua parte de baixo já está completamente nua… ",
            "Eu gostaria de poder ter uma visão mais próxima…"
        ],
        "4": [
            "Merda, eu abri a porta de mais…!"
        ],
        "5": [
            "…Essa foi uma boa visão~        \\w[30]",
            "Eu deveria cair fora agora."
        ],
        "6": [
            "O que eu devo fazer em seguida? ",
            "Infiltrar mais a fundo no banheiro?"
        ],
        "7": [
            "Infiltrar",
            "Voltar"
        ],
        "8": [
            "Se eu continuar, ",
            "Eu posso achar algo a mais…!"
        ],
        "9": [
            "É o suficiente pra hoje. ",
            "Seria ruim se a \\str[120] me pegasse."
        ],
        "10": [
            "…\\str[120] me percebeu espiando!",
            "Eu fui chutado na hora."
        ]
    },
    "25": {
        "0": [
            "\nl< >\"O-\\str[121]!? Por que você está aqui?\""
        ],
        "1": [
            "\nl< >\"…É você atrás da porta, \\str[121]?\""
        ],
        "2": [
            "Guh…!",
            "Então eu fui descoberto a final."
        ],
        "3": [
            "\nl< >\"Eu sabia que era você \\str[121]. ",
            "Por qual motivo você tá se esgueirando por aí?\""
        ],
        "4": [
            "\nl< >\"…\\str[121]?    \\w[30]",
            "O que você tá fazendo se escondendo atrás da porta?\""
        ],
        "5": [
            "Eu já me infiltrei…",
            "Não tem como voltar agora…!"
        ],
        "6": [
            "Eu fui pego espiando…",
            "Como eu devo explicar isso pra \\str[120]…"
        ],
        "7": [
            "Verificando a Saúde",
            "Eu quero te ver!",
            "Inventar Desculpa",
            "Último Recurso",
            "Quero Obscenidade!"
        ],
        "8": [
            "Ahhh…! Parece que eu não tenho ",
            "escolha se não usar o último recurso!"
        ],
        "9": [
            "\"VAMOS FUGIR DAQUI!!!\/""
        ],
        "10": [
            "Eu rapidamente corri do local.      \\w[30]",
            "Mas claro, que mesmo depois disso, ",
            "Eu ainda acabei sendo repreendido pela \\str[120]."
        ],
        "11": [
            "\\{",
            "……Eu fazendo aqui?!",
            "Agora?! Aqui?!"
        ],
        "12": [
            "\nl< >\"\\str[121]!? Você tá me espiando denovo…!?\""
        ],
        "13": [
            "…Parece que a \\str[120] me pegou espiando!",
            "Mas, será que eu estou imaginando coisas?",
            "Parece que ela até está me movendo ",
            "sua buceta pra um ângulo que eu consiga ver——"
        ],
        "14": [
            "\"Se acalma, Querida \\str[120].",
            "\\str[121] definitivamente não está aqui pra fazer nada de ruim.\""
        ],
        "15": [
            "\\{\"Eu só queria observar ",
            "minha adorável irmãzinha pelas sombras！\""
        ],
        "16": [
            "\"Isso aí, é só uma verificação de saúde！\""
        ],
        "17": [
            "\nl< >\"Eu já escutei essa desculpa antes！\""
        ],
        "18": [
            "\"Não não! ",
            "É completamente diferente da última vez！\""
        ],
        "19": [
            "\nl< >\"O—o que você quer dizer…",
            "Por que o \\str[121] faria algo como isso……\""
        ],
        "20": [
            "\"Isso é extremamente importante!",
            "Se houvesse algo de errado com o seu corpo",
            "e eu como seu irmão não percebesse……！\""
        ],
        "21": [
            "\nl< >\"Ughhh… Então o que o \\str[121] quer fazer exatamente？\""
        ],
        "22": [
            "\"Me deixe ver seus peitos primeiro\"    \\w[40]\\^"
        ],
        "23": [
            "Ah—droga. ",
            "Eu acidentalmente falei o que eu estava realmente pensando..."
        ],
        "24": [
            "\nl< >\"…Isso realmente tem algo haver com o que você você queria fazer?\""
        ],
        "25": [
            "\nl< >\"Tá, se o \\str[121] realmente quer ver eles…     \\w[120]",
            "\\}Você é um baita trapaceiro…\\{\""
        ],
        "26": [
            "\nl< >\"Aqui, feliz agora？\""
        ],
        "27": [
            "\"Ah, s-sim… Muito bonito.\""
        ],
        "28": [
            "Eu não achei que a \\str[120] realmente ia me mostrar seus peitos.",
            "Eu fiquei tão chocado que eu mal consegui ver direito."
        ],
        "29": [
            "\nl< >\"Ok, isso é o suficiente!",
            "\\str[121] terminou com o seu exame médico, certo?",
            "Agora eu vou tomar banho, cai fora daqui agora！\""
        ],
        "30": [
            "\nl< >\\{",
            "\"Nem pensar! \\str[121], seu idiota！\""
        ],
        "31": [
            "Eu fui expulso do banheiro pela \\str[120].      \\w[30]",
            "…Será que essa desculpa vai funcionar na próxima vez?"
        ],
        "32": [
            "\"Na verdade, \\str[120]… O \\str[121] tem essa doença",
            "que ele vai morrer caso ele não veja nudez……！\""
        ],
        "33": [
            "Isso foi só uma desculpa que eu inventei na hora ",
            "Mas eu ainda consegui fazer uma expressão convincente de dor."
        ],
        "34": [
            "\nl< >\"Eh!? \\str[121] tem uma doença como essa!?\""
        ],
        "35": [
            "\"Eu nem me lembro quando eu adiquiri ela…",
            "Mas quando ela aflora, meu corpo todo começa a coçar,",
            "e só para quando eu vejo alguém pelado！\""
        ],
        "36": [
            "\nl< >\"Pera, isso é mesmo uma doença real?\""
        ],
        "37": [
            "\"Ah… ahhh…!! A coçeira tá começando…！\""
        ],
        "38": [
            "Eu me joguei no chão de propósito,",
            "me tremendo todo, e obviamente fingindo tudo."
        ],
        "39": [
            "\nl< >\\{\"…………………………\""
        ],
        "40": [
            "\nl< >\"Tá, tá…",
            "Se você tá indo tão longe pra isso, Eu vou te deixar ver…\""
        ],
        "41": [
            "Minha doce e inocente \\str[120] acreditou em mim na hora ",
            "e seu rosto se tornou adoravelmente envergonhado."
        ],
        "42": [
            "\nl< >\"Então, satisfeito agora？\""
        ],
        "43": [
            "Ela era tão fofa,",
            "eu acabei olhando de mais ",
            "e esqueci de manter a atuação."
        ],
        "44": [
            "\nl< >\"…Então, você não está mais com coçeira?\""
        ],
        "45": [
            "\"Yup, eu mee sinto totalmente revigorado.\""
        ],
        "46": [
            "Eu rapidamente me levantei do chão ",
            "e dei um sorriso satisfeito pra ela."
        ],
        "47": [
            "\nl< >\"Ughhh…! Você só tava brincando comigo ",
            "esse tempo todo, não estava!?\""
        ],
        "48": [
            "\nl< >\"\\str[121] você é um completo idiotat! ",
            "Sai daqui agora！\""
        ],
        "49": [
            "Com as bochechas inchadas de frustração, ",
            "\\str[120] me empurrou pra fora do banheiro.",
            "Hmm… acho que acabei estragando as coisas no final."
        ],
        "50": [
            "\nl< >\"Eh!? \\str[121] quer ver meus…!?\""
        ],
        "51": [
            "\nl< >\"Sem chance! \\str[121], você é um palhaço！\""
        ],
        "52": [
            "\nl< >\"Por que diabos você ia pedir uma coisa desse tipo!? ",
            "Isso é muito estranho…！\""
        ],
        "53": [
            "\nl< >\\{\"Geez, \\str[121], seu grande palhaço!!!\""
        ],
        "54": [
            "\\str[120] raivosamente me chutou pra fora.",
            "Talvez eu realmente fui longe demais dessa vez…"
        ]
    },
    "32": {
        "0": [
            "Já que a \\str[120] me chamou, ",
            "Eu nem pensei muito e só entrei direto no banheiro.    \\w[30]\\{",
            "Bem, foi ela que me chamou mesmo."
        ],
        "1": [
            "\"O que aconteceu?\""
        ],
        "2": [
            "\nl< >\"Um... acabou o shampoo.",
            "\\str[121], você poderia me pegar um frasco novo?\""
        ],
        "3": [
            "\\str[120] envergonhadamente botou sua cabeça pra fora do box,",
            "como um animalzinho espiado mas curioso—",
            "do tipo que faz você querer provocar ela ainda mais…",
            "O que eu devo fazer agora?"
        ],
        "4": [
            "Pedir pra \\str[120] sair",
            "Levar o Shampoo"
        ],
        "5": [
            "\nl< >\"Eh... Eu ainda to no meio do banho…\""
        ],
        "6": [
            "\nl< >\"Geez, eu só te chamei porque ",
            "eu não quero molhar o chão…\""
        ],
        "7": [
            "Eu rapidamente espantei esse tipo de pensamentos estranhos,",
            "peguei um frasco novo de shampoo do armário, ",
            "e entreguei para a \\str[120]."
        ],
        "8": [
            "\nl< >\"Obrigada, \\str[121]!",
            "Eu vou voltar pro banho agora-te vejo logo mais!\""
        ],
        "9": [
            "\\str[120] fechou a porta e voltou pro banho.   \\w[30]",
            "Hmm... será que devo ficar um pouco mais?"
        ],
        "10": [
            "Explorar",
            "Voltar"
        ],
        "11": [
            "Já que eu já estou aqui, ",
            "não tem problema dar uma olhada ao redor!"
        ],
        "12": [
            "\\str[120]’s ainda está no banho... melhor voltar."
        ],
        "13": [
            "\\str[120] obediently walked over to me.",
            "Since she was still bathing, ",
            "she only had a towel wrapped loosely around her,",
            "her body giving off the scent of body wash mixed with steam."
        ],
        "14": [
            "Então... ",
            "o que eu devo fazer com a \\str[120] agora...?"
        ],
        "15": [
            "Dar um Kompeitō",
            "Fazer um cafuné",
            "Apertar os peitos",
            "Conversar um pouco"
        ],
        "16": [
            "\"Boa garota, boa garota~ ",
            "Aqui, um docinho pra você.\""
        ],
        "17": [
            "\nl< >\"Eu já tenho—    \\w[70]\\^"
        ],
        "18": [
            "\nl< >\"E mesmo que tenha um gosto muito bom,",
            "ele sempre deixa meu corpo meio quente depois…\""
        ],
        "19": [
            "\nl< >\"Docinho, huh... tão doce...      \\w[60]",
            "Mas \\str[121], você tá parecendo um vovozinho, sabe?\""
        ],
        "20": [
            "Eu fiz a \\str[120] comer um Kompeitō estranho."
        ],
        "21": [
            "\nl< >\"Eu disse pra parar de encostar em mim agora!\""
        ],
        "22": [
            "\"    ヾ(・ω・｀)    ",
            "Boa garota, boa garota~\""
        ],
        "23": [
            "\nl< >\"Mmm...    \\w[45]",
            "Meu cabelo ainda tá molhado,",
            "então não meche nele agora…\""
        ],
        "24": [
            "Eu dei um cafuné pelo cabelo encharcado da \\str[120]—",
            "pois é, a textura estava bem ruim…"
        ],
        "25": [
            "\nl< >\"\\str[121]... você ao menos lembra o porque você veio aqui...?\""
        ],
        "26": [
            "\nl< >\"Se voê tá assim desesperado, \\str[121], é so dizer não...",
            "Você está sempre pensando nesse tipo de coisa mesmo…\""
        ],
        "27": [
            "\nl< >\"Então tua mão só escorregou, de novo...?   \\w[90]\\{",
            "\\str[121] seu pervertido!\""
        ],
        "28": [
            "Admirando as curvas delineadas da \\str[120] através da toalha, minha mão ",
            "se moveu sozinha, alcançando para apertar aqueles pesados, quentes e macios..."
        ],
        "29": [
            "\nl< >\\{\"—Nyaaah!?\\str[121]!?\""
        ],
        "30": [
            "\"Desculpa, minha mão escorregou.\""
        ],
        "31": [
            "\nl< >\"Essa não é a hora pra me provocar...!\""
        ],
        "32": [
            "Mmm... julgando pelo toque,",
            "parece que a \\str[120] cresceu um pouco mais."
        ],
        "33": [
            "\nl< >\"Já deu... cadê o meu shampoo?\""
        ],
        "34": [
            "\"A temperatura da água está boa?\""
        ],
        "35": [
            "\nl< >\"Está perfeita, muiuto confortável.\""
        ],
        "36": [
            "Conversei casualmente com a \\str[120] um pouquinho."
        ],
        "37": [
            "Hmm, Eu já passei muito tempo aqui. ",
            "Melhor parar de provocar a\\str[120]",
            "e pegar o shampoo pra ela."
        ],
        "38": [
            "\nl< >\"Obrigada, \\str[121]! ",
            "Eu vou voltar pro banho, te vejo daqui a pouco~\""
        ],
        "39": [
            "\\str[120] fechou a porta e voltou pro banho.    \\w[30]",
            "Se eu ficar mais tempo, vai parecer suspeito... Eu devo voltar."
        ],
        "40": [
            "\nl< >\\{\"—Nyaaah!?\"",
            "\\w[45]\\^"
        ],
        "41": [
            "\\str[120] caiu de repente bem na minha frente,",
            "caindo de cara no chão—",
            "ver ela caindo doeu até em mim..."
        ],
        "42": [
            "\\{\"Ah! Você... ",
            "Você tá bem!?\""
        ],
        "43": [
            "Eu rapidamente corri para ajudar a \\str[120] se levantar.",
            "Felizmente, não pareceu uma queda dura, ela não se machucou."
        ],
        "44": [
            "\nl< >\"Uuuuh... \\str[121], isso realmente doeu...\""
        ],
        "45": [
            "\nl< >\"Acho que vou ficar com um galo na cabeça...!\""
        ],
        "46": [
            "Vendo a \\str[120] tremendo levemente de dor,",
            "eu gentilmente confortei ela e a ajudei a voltar pro banho ",
            "pra ela poder lavar seu cabelo."
        ]
    }
}
